Workbook

Sheet Sales Dashboard
A1: SUPERMARKET SALES ANALYSIS DASHBOARD
A3: Total Revenue | D3: Total Orders | H3: Total Quantity Sold | O3: Average Order Value
A4: ='Sales Analysis'!B2 -> 10855.152 | D4: ='Sales Analysis'!B3 -> 70 | H4: ='Sales Analysis'!B4 -> 168 | O4: ='Sales Analysis'!B5 -> 155.0736

Sheet Sales Analysis
A1: SALES METRICS | B1: VALUE
A2: Total Revenue | B2: =SUM('SuperMarket Sales'!H2:H71) -> 10855.152
A3: Total Orders | B3: =COUNTA('SuperMarket Sales'!A2:A71) -> 70
A4: Total Quantity Sold | B4: =SUM('SuperMarket Sales'!F2:F71) -> 168
A5: Average Order Value | B5: =AVERAGE('SuperMarket Sales'!H2:H71) -> 155.0736
A6: Highest Sale | B6: =MAX('SuperMarket Sales'!H2:H71) -> 329.967
A7: Lowest Sale | B7: =MIN('SuperMarket Sales'!H2:H71) -> 32.989
A8: Sales from Orders above or equal to 5 units | B8: =SUMIF('SuperMarket Sales'!F2:F71,">=5",'SuperMarket Sales'!H2:H71) -> 1154.615
A9: Count Orders above or equal to 5 units | B9: =COUNTIF('SuperMarket Sales'!A2:A71,">=5") -> 70
A10: Average Shipping Days | B10: =AVERAGE('SuperMarket Sales'!I2:I71) -> 2.9
A11: Revenue from Large Orders | B11: =SUMIF('SuperMarket Sales'!J2:J71,"Large Order", 'SuperMarket Sales'!H2:H71) -> 1154.615
A12: Revenue from Small Orders | B12: =SUMIF('SuperMarket Sales'!J2:J71,"Small Order", 'SuperMarket Sales'!H2:H71) -> 9700.537
A13: Number of Large Orders | B13: =COUNTIF('SuperMarket Sales'!J2:J71,"Large Order") -> 7
A14: Number of Small Orders | B14: =COUNTIF('SuperMarket Sales'!J2:J71,"Small Order") -> 63
A15: Revenue from Orders above or equal to 5 units with a Total above $100 | B15: =SUMIFS('SuperMarket Sales'!H2:H71,'SuperMarket Sales'!F2:F71,">=5",'SuperMarket Sales'!H2:H71,">$100") -> 1154.615
A16: Percentage of Large Orders | B16: =COUNTIF('SuperMarket Sales'!J2:J71,"Large Order")/COUNTA('SuperMarket Sales'!A2:A71) -> 0.1
A17: Average Order Quantity | B17: =AVERAGE('SuperMarket Sales'!F2:F71) -> 2.4
A18: Total Sales for January | B18: =SUMIF('SuperMarket Sales'!K2:K71,"January",'SuperMarket Sales'!H2:H71) -> 9601.372
A19: Total Sales for February | B19: =SUMIF('SuperMarket Sales'!K2:K71,"February",'SuperMarket Sales'!H2:H71) -> 1253.78

Sheet Monthly Sales
A3: Row Labels | B3: Sum of Total (USD)
A4: January | B4: 9601.372
A5: February | B5: 1253.78
A6: Grand Total | B6: 10855.152

Sheet Customer Sales
A3: Row Labels | B3: Sum of Total (USD)
A4: Jane Doe | B4: 32.989
A5: David Brown | B5: 87.956
A6: Matthew Wilson | B6: 87.956
A7: Christopher Thomas | B7: 98.989
A8: John Smith | B8: 109.978
A9: Emily Rodriguez | B9: 131.967
A10: Laura Brown | B10: 131.967
A11: Daniel Martinez | B11: 131.967
A12: Matthew Johnson | B12: 131.967
A13: Jessica Johnson | B13: 142.989
A14: Christopher Rodriguez | B14: 142.989
A15: Jessica Gonzalez | B15: 142.989
... A55: Grand Total | B55: 10855.152

Sheet Order Sales
A1: Row Labels | B1: Sum of Total (USD)
A2: Large Order | B2: 1154.615
A3: Small Order | B3: 9700.537
A4: Grand Total | B4: 10855.152

Sheet Quantity Sales
A3: Row Labels | B3: Sum of Total (USD)
A4: 1 | B4: 3992.736
A5: 2 | B5: 2595.648
A6: 3 | B6: 2408.505
A7: 4 | B7: 703.648
A8: 5 | B8: 1154.615
A9: Grand Total | B9: 10855.152

Sheet Shipping Perfomance
A3: Row Labels | B3: Sum of Order No
A4: 1 | B4: 16619
A5: 2 | B5: 14536
A6: 3 | B6: 13447
A7: 4 | B7: 15621
A8: 5 | B8: 12262
A9: Grand Total | B9: 72485

Sheet Data Inspection
A1: DATA INSPECTION : INSPECTION OF RAW DATA
A2: INSPECTION TASK | B2: WHAT WAS CHECKED | C2: RESULT | D2: STATUS | E2: ACTION
A3: Dataset Size | B3: Number of rows and columns | C3: 70 rows , 8 columns | D3: PASS | E3: None
A4: Header row | B4: Dataset headers | C4: 8 rows were identified | D4: PASS | E4: None
A5: Data Types | B5: Column data types | C5: Some numeric values were stored as text | D5: ISSUE FOUND | E5: Converted text values to numbers
A6: Missing Values | B6: Blank cells | C6: None Found | D6: PASS | E6: None
A7: Duplicate Orders | B7: Order No | C7: None Found | D7: PASS | E7: None
A8: Date Validity | B8: Order Date & Ship Date | C8: All Dates appear valid | D8: PASS | E8: None
A9: Shipping Sequence | B9: Ship Date >= Order Date | C9: No Invalid sequences found | D9: PASS | E9: None
A10: Retail Price | B10: Zero/Negative/Unusual values | C10: No Invalid values found | D10: PASS | E10: None
A11: Order Quantity | B11: Zero/Negative/Unusual values | C11: No Invalid values found | D11: PASS | E11: None
A12: Tax | B12: Zero/Negative/Unusual values | C12: No Invalid values found | D12: PASS | E12: None
A13: Total | B13: Zero/Negative/Unusual values | C13: No Invalid values found | D13: PASS | E13: None
... A20: Final Data Quality | B20: Columns, range and dataset structure | C20: Dataset structure appears suitable for cleaning | D20: PASS | E20: None

Sheet SuperMarket Sales
A1: Order No | B1: Order Date | C1: Customer Name | D1: Ship Date | E1: Retail Price (USD) | F1: Order Quantity | G1: Tax (USD) | H1: Total (USD) | I1: Shipping Days | J1: Order Size Category | K1: Order Month
A2: 1001 | B2: 45292 | C2: John Smith | D2: 45294 | E2: 49.99 | F2: 2 | G2: =E2*F2*10% -> 9.998 | H2: =E2*F2+G2 -> 109.978 | I2: =D2-B2 -> 2 | J2: =IF('SuperMarket Sales'!F2>=5, "Large Order", "Small Order") -> Small Order | K2: =TEXT(B2,"mmmm") -> January
A3: 1002 | B3: 45292 | C3: Jane Doe | D3: 45295 | E3: 29.99 | F3: 1 | G3: =E3*F3*10% -> 2.999 | H3: =E3*F3+G3 -> 32.989 | I3: =D3-B3 -> 3 | J3: =IF('SuperMarket Sales'!F3>=5, "Large Order", "Small Order") -> Small Order | K3: =TEXT(B3,"mmmm") -> January
A4: 1003 | B4: 45293 | C4: Michael Johnson | D4: 45298 | E4: 99.99 | F4: 3 | G4: =E4*F4*10% -> 29.997 | H4: =E4*F4+G4 -> 329.967 | I4: =D4-B4 -> 5 | J4: =IF('SuperMarket Sales'!F4>=5, "Large Order", "Small Order") -> Small Order | K4: =TEXT(B4,"mmmm") -> January
A5: 1004 | B5: 45293 | C5: Emily Brown | D5: 45294 | E5: 19.99 | F5: 4 | G5: =E5*F5*10% -> 7.996 | H5: =E5*F5+G5 -> 87.956 | I5: =D5-B5 -> 1 | J5: =IF('SuperMarket Sales'!F5>=5, "Large Order", "Small Order") -> Small Order | K5: =TEXT(B5,"mmmm") -> January
A6: 1005 | B6: 45294 | C6: David Wilson | D6: 45299 | E6: 149.99 | F6: 1 | G6: =E6*F6*10% -> 14.999 | H6: =E6*F6+G6 -> 164.989 | I6: =D6-B6 -> 5 | J6: =IF('SuperMarket Sales'!F6>=5, "Large Order", "Small Order") -> Small Order | K6: =TEXT(B6,"mmmm") -> January
A7: 1006 | B7: 45294 | C7: Lisa Taylor | D7: 45297 | E7: 79.99 | F7: 2 | G7: =E7*F7*10% -> 15.998 | H7: =E7*F7+G7 -> 175.978 | I7: =D7-B7 -> 3 | J7: =IF('SuperMarket Sales'!F7>=5, "Large Order", "Small Order") -> Small Order | K7: =TEXT(B7,"mmmm") -> January
A8: 1007 | B8: 45295 | C8: Daniel Martinez | D8: 45297 | E8: 39.99 | F8: 3 | G8: =E8*F8*10% -> 11.997 | H8: =E8*F8+G8 -> 131.967 | I8: =D8-B8 -> 2 | J8: =IF('SuperMarket Sales'!F8>=5, "Large Order", "Small Order") -> Small Order | K8: =TEXT(B8,"mmmm") -> January
A9: 1008 | B9: 45295 | C9: Sarah Anderson | D9: 45300 | E9: 69.99 | F9: 2 | G9: =E9*F9*10% -> 13.998 | H9: =E9*F9+G9 -> 153.978 | I9: =D9-B9 -> 5 | J9: =IF('SuperMarket Sales'!F9>=5, "Large Order", "Small Order") -> Small Order | K9: =TEXT(B9,"mmmm") -> January
A10: 1009 | B10: 45296 | C10: Christopher Thomas | D10: 45297 | E10: 89.99 | F10: 1 | G10: =E10*F10*10% -> 8.999 | H10: =E10*F10+G10 -> 98.989 | I10: =D10-B10 -> 1 | J10: =IF('SuperMarket Sales'!F10>=5, "Large Order", "Small Order") -> Small Order | K10: =TEXT(B10,"mmmm") -> January
A11: 1010 | B11: 45296 | C11: Kimberly Garcia | D11: 45299 | E11: 199.99 | F11: 1 | G11: =E11*F11*10% -> 19.999 | H11: =E11*F11+G11 -> 219.989 | I11: =D11-B11 -> 3 | J11: =IF('SuperMarket Sales'!F11>=5, "Large Order", "Small Order") -> Small Order | K11: =TEXT(B11,"mmmm") -> January
A12: 1011 | B12: 45297 | C12: William Hernandez | D12: 45298 | E12: 29.99 | F12: 5 | G12: =E12*F12*10% -> 14.995 | H12: =E12*F12+G12 -> 164.945 | I12: =D12-B12 -> 1 | J12: =IF('SuperMarket Sales'!F12>=5, "Large Order", "Small Order") -> Large Order | K12: =TEXT(B12,"mmmm") -> January
A13: 1012 | B13: 45297 | C13: Melissa Lopez | D13: 45299 | E13: 79.99 | F13: 2 | G13: =E13*F13*10% -> 15.998 | H13: =E13*F13+G13 -> 175.978 | I13: =D13-B13 -> 2 | J13: =IF('SuperMarket Sales'!F13>=5, "Large Order", "Small Order") -> Small Order | K13: =TEXT(B13,"mmmm") -> January
... A71: 1070 | B71: 45326 | C71: Jennifer Hernandez | D71: 45329 | E71: 149.99 | F71: 1 | G71: =E71*F71*10% -> 14.999 | H71: =E71*F71+G71 -> 164.989 | I71: =D71-B71 -> 3 | J71: =IF('SuperMarket Sales'!F71>=5, "Large Order", "Small Order") -> Small Order | K71: =TEXT(B71,"mmmm") -> February
